clnvm/__init__.py
clnvm/__main__.py
clnvm/cli.py
clnvm/cln_version_manager.py
clnvm/errors.py
clnvm/py.typed
clnvm/utils.py
cln_version_manager-0.1.0.dist-info/METADATA
cln_version_manager-0.1.0.dist-info/WHEEL
cln_version_manager-0.1.0.dist-info/entry_points.txt
cln_version_manager-0.1.0.dist-info/RECORD
