Metadata-Version: 2.1
Name: cln-version-manager
Version: 0.1.0
Summary: A version manager for Core Lightning Binaries
License: MIT
Author: Erik De Smedt
Author-email: edesmedt@blockstream.com
Requires-Python: >=3.8,<4.0
Classifier: License :: OSI Approved :: MIT License
Classifier: Programming Language :: Python :: 3
Classifier: Programming Language :: Python :: 3.8
Classifier: Programming Language :: Python :: 3.9
Classifier: Programming Language :: Python :: 3.10
Classifier: Programming Language :: Python :: 3.11
Classifier: Programming Language :: Python :: 3.12
Requires-Dist: click (>=8,<9)
Requires-Dist: requests (>=2,<3)
